pycounts_vs/__init__.py
pycounts_vs/plotting.py
pycounts_vs/pycounts_vs.py
pycounts_vs-0.5.0.dist-info/LICENSE
pycounts_vs-0.5.0.dist-info/WHEEL
pycounts_vs-0.5.0.dist-info/METADATA
pycounts_vs-0.5.0.dist-info/RECORD
