Metadata-Version: 2.1
Name: pycounts-vs
Version: 0.5.0
Summary: Calculate word counts in a text file!
License: MIT
Author: Tomas Beuzen
Requires-Python: >=3.9
Classifier: License :: OSI Approved :: MIT License
Classifier: Programming Language :: Python :: 3
Classifier: Programming Language :: Python :: 3.10
Classifier: Programming Language :: Python :: 3.9
Requires-Dist: matplotlib (>=3.5.1)
